MANIFEST.in
README.rst
setup.py
aliyun_python_sdk_tdsr.egg-info/PKG-INFO
aliyun_python_sdk_tdsr.egg-info/SOURCES.txt
aliyun_python_sdk_tdsr.egg-info/dependency_links.txt
aliyun_python_sdk_tdsr.egg-info/requires.txt
aliyun_python_sdk_tdsr.egg-info/top_level.txt
aliyunsdktdsr/__init__.py
aliyunsdktdsr/endpoint.py
aliyunsdktdsr/request/__init__.py
aliyunsdktdsr/request/v20200101/CheckPermissionRequest.py
aliyunsdktdsr/request/v20200101/CheckResourceRequest.py
aliyunsdktdsr/request/v20200101/CreateProjectRequest.py
aliyunsdktdsr/request/v20200101/CreateSceneRequest.py
aliyunsdktdsr/request/v20200101/DeleteFileRequest.py
aliyunsdktdsr/request/v20200101/DeleteProjectRequest.py
aliyunsdktdsr/request/v20200101/GetHotspotConfigRequest.py
aliyunsdktdsr/request/v20200101/GetHotspotTagRequest.py
aliyunsdktdsr/request/v20200101/GetPolicyRequest.py
aliyunsdktdsr/request/v20200101/GetSceneDataRequest.py
aliyunsdktdsr/request/v20200101/GetSceneListRequest.py
aliyunsdktdsr/request/v20200101/GetWindowConfigRequest.py
aliyunsdktdsr/request/v20200101/ListMainScenesRequest.py
aliyunsdktdsr/request/v20200101/ListScenesRequest.py
aliyunsdktdsr/request/v20200101/PublishHotspotRequest.py
aliyunsdktdsr/request/v20200101/SaveFileRequest.py
aliyunsdktdsr/request/v20200101/SaveHotspotConfigRequest.py
aliyunsdktdsr/request/v20200101/SaveHotspotTagRequest.py
aliyunsdktdsr/request/v20200101/__init__.py